segment/__init__.py
segment/segment.py
segment/data/__init__.py
segment/data/fetch.py
segment/data/test_data/test_sub_01.PAR
segment/data/test_data/test_sub_01.REC
segment/data/test_data/test_sub_01.hdr
segment/data/test_data/test_sub_01.img
segment/data/test_data/test_sub_01.nii
segment/data/test_data/test_sub_01.nii.gz
segment/data/test_data/test_sub_02.PAR
segment/data/test_data/test_sub_02.REC
segment/data/test_data/test_sub_02.hdr
segment/data/test_data/test_sub_02.img
segment/data/test_data/test_sub_02.nii
segment/data/test_data/test_sub_02.nii.gz
segment/data/tests/__init__.py
segment/data/tests/test_fetch.py
segment/tests/__init__.py
segment/tests/test_tkv.py
segment/tests/utils.py
renalsegmentor-1.3.12.dist-info/LICENSE.txt
renalsegmentor-1.3.12.dist-info/METADATA
renalsegmentor-1.3.12.dist-info/WHEEL
renalsegmentor-1.3.12.dist-info/top_level.txt
renalsegmentor-1.3.12.dist-info/RECORD
