Metadata-Version: 2.1
Name: renalsegmentor
Version: 1.3.12
Summary: Segment kidneys from MRI data
Home-page: https://github.com/alexdaniel654/Renal_Segmentor
License: GPL-3.0
Platform: UNKNOWN
Classifier: Development Status :: 5 - Production/Stable
Classifier: Intended Audience :: Developers
Classifier: Intended Audience :: Science/Research
Classifier: Topic :: Scientific/Engineering
Classifier: Environment :: Console
Classifier: Operating System :: OS Independent
Classifier: Programming Language :: Python :: 3
Classifier: Programming Language :: Python :: 3.8
Classifier: Programming Language :: Python :: 3.9
Classifier: Programming Language :: Python :: 3.10
Classifier: Programming Language :: Python :: 3.11
Classifier: Programming Language :: Python :: 3.12
Classifier: License :: OSI Approved :: GNU General Public License v3 (GPLv3)
Requires-Python: >=3.8, <4
Requires-Dist: nibabel>=5.1.0
Requires-Dist: numpy>=1.24.2
Requires-Dist: pandas>=2.0.3
Requires-Dist: pytest>=7.4.0
Requires-Dist: scikit-image>=0.20.0
Requires-Dist: keras>2
Requires-Dist: wget>=3.2
Requires-Dist: tensorflow>=2.13.0; sys_platform == "darwin"
Requires-Dist: tensorflow>=2.13.0; sys_platform == "linux"
Requires-Dist: tensorflow-cpu>=2.13.0; sys_platform == "win32"
Provides-Extra: gui
Requires-Dist: pyinstaller~=5.3; extra == "gui"
Requires-Dist: Gooey~=1.0.8.1; extra == "gui"
